anyfont/__init__.py
anyfont/candidates.py
anyfont/towoff2.py
anyfont/woff2css.py
anyfont/woff2ff.py
anyfont-1.0.4.dist-info/METADATA
anyfont-1.0.4.dist-info/WHEEL
anyfont-1.0.4.dist-info/entry_points.txt
anyfont-1.0.4.dist-info/top_level.txt
anyfont-1.0.4.dist-info/RECORD
