Metadata-Version: 2.1
Name: anyfont
Version: 1.0.4
Summary: A powerful css and woff from ttf or anything for font management
Home-page: https://github.com/acalasanzs/AnyFont
Author: Albert Calasanz Sallen
Author-email: acalasanzs@gmail.com
Project-URL: Bug Tracker, https://github.com/acalasanzs/AnyFont/issues
Classifier: Programming Language :: Python :: 3
Classifier: License :: OSI Approved :: MIT License
Classifier: Operating System :: OS Independent
Requires-Python: >=3.6
Requires-Dist: brotli
Requires-Dist: fontTools
